lightbulb/ext/wtf/__init__.py
lightbulb/ext/wtf/base.py
lightbulb/ext/wtf/basic.py
lightbulb/ext/wtf/commands.py
lightbulb/ext/wtf/executable.py
lightbulb/ext/wtf/options.py
lightbulb/ext/wtf/py.typed
lightbulb_ext_wtf-0.1.0.dist-info/LICENSE
lightbulb_ext_wtf-0.1.0.dist-info/METADATA
lightbulb_ext_wtf-0.1.0.dist-info/WHEEL
lightbulb_ext_wtf-0.1.0.dist-info/top_level.txt
lightbulb_ext_wtf-0.1.0.dist-info/RECORD
